qqabc/__init__.py
qqabc/config.py
qqabc/py.typed
qqabc/qq.py
qqabc/types.py
qqabc/rurl/__init__.py
qqabc/rurl/basic.py
qqabc/rurl/rurl.py
qqabc-0.2.1.dist-info/METADATA
qqabc-0.2.1.dist-info/WHEEL
qqabc-0.2.1.dist-info/licenses/LICENSE
qqabc-0.2.1.dist-info/RECORD
