Metadata-Version: 2.4
Name: qqabc
Version: 0.2.1
Summary: Simple Message Queue Implementation
Project-URL: Homepage, https://github.com/HYChou0515/qqabc
Project-URL: Documentation, https://HYChou0515.github.io/qqabc/
Project-URL: Repository, https://github.com/HYChou0515/qqabc.git
Project-URL: Issues, https://github.com/HYChou0515/qqabc/issues
Author-email: Chou Hung-Yi <hychou.svm@gmail.com>
License: MIT License
License-File: LICENSE
Keywords: message-queue,mq,multiprocessing,threading
Classifier: Development Status :: 4 - Beta
Classifier: Intended Audience :: Developers
Classifier: License :: OSI Approved :: MIT License
Classifier: Operating System :: OS Independent
Classifier: Programming Language :: Python :: 3
Classifier: Programming Language :: Python :: 3.8
Classifier: Programming Language :: Python :: 3.9
Classifier: Programming Language :: Python :: 3.10
Classifier: Programming Language :: Python :: 3.11
Classifier: Programming Language :: Python :: 3.12
Classifier: Programming Language :: Python :: 3.13
Classifier: Topic :: Software Development :: Libraries :: Python Modules
Requires-Python: >=3.8
Requires-Dist: multiprocess~=0.70.14
Requires-Dist: typing-extensions; python_version <= '3.10'
Provides-Extra: httpx
Requires-Dist: httpx>=0.28.1; extra == 'httpx'
